{
  "online": true,
  "playing": false,
  "rating": 3066,
  "opponent": "llllllllnnuellllllll",
  "variant": "Variant: Standard",
  "time_control": "TC: 1+0",
  "time_left": 32,
  "timestamp": "2025-12-06T08:25:02.290213",
  "last_game": {
    "result": "draw",
    "opponent": "llllllllnnuellllllll",
    "rating_before": 3066,
    "rating_after": 3066,
    "rating_delta": 0,
    "moves": "e4 e5 Nf3 Nc6 Bb5 Nf6 d3 Bc5 Bxc6 dxc6 O-O Nd7 Nbd2 O-O Nc4 f6 Nh4 Rf7 Nf5 Bf8 f4 Nb6 Nce3 exf4 Rxf4 g6 Ng3 Bg7 Qe2 Qd6 Rf2 c5 Bd2 Be6 Raf1 Nd7 Qe1 Ne5 Bc3 b5 b3 Bd7 Ne2 Re8 h3 Bh6 Nf4 Bg5 g3 Nc6 h4 Bh6 a4 a6 h5 f5 hxg6 hxg6 Rh2 Rh7 axb5 axb5 exf5 gxf5 Qf2 Nd4 Bxd4 cxd4 Neg2 Ree7 Ra1 Bc6 Re1 Bxf4 Rxe7 Rxe7 Nxf4 Re3 Rh5 Qe5 g4 Qe7 Ng2 Bxg2 Qxf5 Re1+ Kh2 Ba8 Rg5+ Kh8 Rh5+ Kg8 Rg5+ Kh8 Rh5+ Kg8",
    "duration": 60,
    "bot_color": "black",
    "termination": "draw"
  },
  "updated": 1765009502.2903202
}